StreamDataPanel/__init__.py
StreamDataPanel/__main__.py
StreamDataPanel/api.py
StreamDataPanel/apiCore.py
StreamDataPanel/apiTest.py
StreamDataPanel/config.json
StreamDataPanel/configDefault.json
StreamDataPanel/configEdit.py
StreamDataPanel/web/dango.svg
StreamDataPanel/web/index.html
StreamDataPanel/web/assets/index-35HjzqWS.js
StreamDataPanel/web/assets/index-B8ZQiBAj.css
StreamDataPanel/web/assets/vendor-echarts-Dwmdrxdr.js
StreamDataPanel/web/assets/vendor-echarts-gl-Dy9zB92n.js
StreamDataPanel/web/assets/vendor-main-DSi3UDf9.js
StreamDataPanel/web/assets/vendor-react-HgYf5haI.js
StreamDataPanel/web/assets/vendor-react-grid-layout-p1QaFhf8.js
streamdatapanel-0.1.28.dist-info/licenses/LICENSE
streamdatapanel-0.1.28.dist-info/METADATA
streamdatapanel-0.1.28.dist-info/WHEEL
streamdatapanel-0.1.28.dist-info/entry_points.txt
streamdatapanel-0.1.28.dist-info/top_level.txt
streamdatapanel-0.1.28.dist-info/RECORD
