Metadata-Version: 2.4
Name: StreamDataPanel
Version: 0.1.28
Summary: StreamDataPanel is a web app used to show frequently-freshed data.
Home-page: 
Author: Syuya_Murakami
Author-email: wxy135@mail.ustc.edu.cn
Project-URL: Bug Tracker, https://github.com/SyuyaMurakami/StreamDataPanel
Classifier: Programming Language :: Python :: 3
Classifier: License :: OSI Approved :: MIT License
Classifier: Operating System :: OS Independent
Requires-Python: >=3.8
License-File: LICENSE
Requires-Dist: websockets
Requires-Dist: eel
Dynamic: author
Dynamic: author-email
Dynamic: classifier
Dynamic: description
Dynamic: description-content-type
Dynamic: license-file
Dynamic: project-url
Dynamic: requires-dist
Dynamic: requires-python
Dynamic: summary
